[{"Zug":"RE 1","Fahrzeit inkl. Versp\u00e4tungen [min]":93.5520334928,"Versp\u00e4tung Abfahrt [min]":3.2464114833,"Versp\u00e4tung Ankunft [min]":7.5233253589,"Ausfallquote":0.0772626932,"Stichprobengr\u00f6\u00dfe":1812},{"Zug":"RE 4","Fahrzeit inkl. Versp\u00e4tungen [min]":80.7142857143,"Versp\u00e4tung Abfahrt [min]":2.643902439,"Versp\u00e4tung Ankunft [min]":5.2369337979,"Ausfallquote":0.1212492345,"Stichprobengr\u00f6\u00dfe":1633},{"Zug":"EST","Fahrzeit inkl. Versp\u00e4tungen [min]":75.828358209,"Versp\u00e4tung Abfahrt [min]":10.5298507463,"Versp\u00e4tung Ankunft [min]":13.671641791,"Ausfallquote":0.035971223,"Stichprobengr\u00f6\u00dfe":139},{"Zug":"ICE 1053","Fahrzeit inkl. Versp\u00e4tungen [min]":79.0789473684,"Versp\u00e4tung Abfahrt [min]":6.9736842105,"Versp\u00e4tung Ankunft [min]":7.4210526316,"Ausfallquote":0.1739130435,"Stichprobengr\u00f6\u00dfe":46},{"Zug":"FLX 30","Fahrzeit inkl. Versp\u00e4tungen [min]":70.2666666667,"Versp\u00e4tung Abfahrt [min]":18.5333333333,"Versp\u00e4tung Ankunft [min]":18.8,"Ausfallquote":0.0,"Stichprobengr\u00f6\u00dfe":30},{"Zug":"ICE 1051","Fahrzeit inkl. Versp\u00e4tungen [min]":77.7391304348,"Versp\u00e4tung Abfahrt [min]":5.3913043478,"Versp\u00e4tung Ankunft [min]":5.1304347826,"Ausfallquote":0.1153846154,"Stichprobengr\u00f6\u00dfe":26}]