[{"Zug":"EC 259","Fahrzeit inkl. Versp\u00e4tungen [min]":159.2333333333,"Versp\u00e4tung Abfahrt [min]":9.2333333333,"Versp\u00e4tung Ankunft [min]":25.6333333333,"Ausfallquote":0.1666666667,"Stichprobengr\u00f6\u00dfe":36},{"Zug":"ES","Fahrzeit inkl. Versp\u00e4tungen [min]":167.9285714286,"Versp\u00e4tung Abfahrt [min]":4.4285714286,"Versp\u00e4tung Ankunft [min]":29.2857142857,"Ausfallquote":0.0,"Stichprobengr\u00f6\u00dfe":14},{"Zug":"ICE 2519","Fahrzeit inkl. Versp\u00e4tungen [min]":151.0,"Versp\u00e4tung Abfahrt [min]":0.0,"Versp\u00e4tung Ankunft [min]":16.0,"Ausfallquote":0.0,"Stichprobengr\u00f6\u00dfe":1}]