[{"Zug":"FLX 35","Fahrzeit inkl. Versp\u00e4tungen [min]":126.0816326531,"Versp\u00e4tung Abfahrt [min]":14.7959183673,"Versp\u00e4tung Ankunft [min]":32.2448979592,"Ausfallquote":0.0576923077,"Stichprobengr\u00f6\u00dfe":52},{"Zug":"ICE 706","Fahrzeit inkl. Versp\u00e4tungen [min]":122.375,"Versp\u00e4tung Abfahrt [min]":4.975,"Versp\u00e4tung Ankunft [min]":11.35,"Ausfallquote":0.0909090909,"Stichprobengr\u00f6\u00dfe":44},{"Zug":"ICE 708","Fahrzeit inkl. Versp\u00e4tungen [min]":120.7948717949,"Versp\u00e4tung Abfahrt [min]":3.5384615385,"Versp\u00e4tung Ankunft [min]":13.3333333333,"Ausfallquote":0.1136363636,"Stichprobengr\u00f6\u00dfe":44},{"Zug":"ICE 802","Fahrzeit inkl. Versp\u00e4tungen [min]":122.2564102564,"Versp\u00e4tung Abfahrt [min]":4.4358974359,"Versp\u00e4tung Ankunft [min]":15.6923076923,"Ausfallquote":0.1136363636,"Stichprobengr\u00f6\u00dfe":44},{"Zug":"ICE 804","Fahrzeit inkl. Versp\u00e4tungen [min]":120.7804878049,"Versp\u00e4tung Abfahrt [min]":7.4390243902,"Versp\u00e4tung Ankunft [min]":17.2195121951,"Ausfallquote":0.0681818182,"Stichprobengr\u00f6\u00dfe":44},{"Zug":"ICE 808","Fahrzeit inkl. Versp\u00e4tungen [min]":121.3658536585,"Versp\u00e4tung Abfahrt [min]":2.5365853659,"Versp\u00e4tung Ankunft [min]":13.9024390244,"Ausfallquote":0.0681818182,"Stichprobengr\u00f6\u00dfe":44},{"Zug":"ICE 704","Fahrzeit inkl. Versp\u00e4tungen [min]":131.6551724138,"Versp\u00e4tung Abfahrt [min]":4.8620689655,"Versp\u00e4tung Ankunft [min]":10.7931034483,"Ausfallquote":0.3095238095,"Stichprobengr\u00f6\u00dfe":42},{"Zug":"ICE 908","Fahrzeit inkl. Versp\u00e4tungen [min]":124.6428571429,"Versp\u00e4tung Abfahrt [min]":0.3571428571,"Versp\u00e4tung Ankunft [min]":6.6071428571,"Ausfallquote":0.0967741935,"Stichprobengr\u00f6\u00dfe":31}]