[{"Zug":"ICE 100","Fahrzeit inkl. Versp\u00e4tungen [min]":126.0344827586,"Versp\u00e4tung Abfahrt [min]":20.4482758621,"Versp\u00e4tung Ankunft [min]":14.5517241379,"Ausfallquote":0.1470588235,"Stichprobengr\u00f6\u00dfe":34},{"Zug":"ICE 274","Fahrzeit inkl. Versp\u00e4tungen [min]":85.6875,"Versp\u00e4tung Abfahrt [min]":25.125,"Versp\u00e4tung Ankunft [min]":27.8125,"Ausfallquote":0.0588235294,"Stichprobengr\u00f6\u00dfe":34},{"Zug":"IC 2431","Fahrzeit inkl. Versp\u00e4tungen [min]":133.7142857143,"Versp\u00e4tung Abfahrt [min]":3.7619047619,"Versp\u00e4tung Ankunft [min]":6.4761904762,"Ausfallquote":0.0869565217,"Stichprobengr\u00f6\u00dfe":23},{"Zug":"ICE 790","Fahrzeit inkl. Versp\u00e4tungen [min]":96.8823529412,"Versp\u00e4tung Abfahrt [min]":12.4705882353,"Versp\u00e4tung Ankunft [min]":17.3529411765,"Ausfallquote":0.15,"Stichprobengr\u00f6\u00dfe":20},{"Zug":"IC 2035","Fahrzeit inkl. Versp\u00e4tungen [min]":132.9411764706,"Versp\u00e4tung Abfahrt [min]":3.8235294118,"Versp\u00e4tung Ankunft [min]":3.3529411765,"Ausfallquote":0.1052631579,"Stichprobengr\u00f6\u00dfe":19},{"Zug":"ICE 2520","Fahrzeit inkl. Versp\u00e4tungen [min]":80.7272727273,"Versp\u00e4tung Abfahrt [min]":19.7272727273,"Versp\u00e4tung Ankunft [min]":13.5454545455,"Ausfallquote":0.0,"Stichprobengr\u00f6\u00dfe":11},{"Zug":"ICE 655","Fahrzeit inkl. Versp\u00e4tungen [min]":124.25,"Versp\u00e4tung Abfahrt [min]":9.5,"Versp\u00e4tung Ankunft [min]":18.0,"Ausfallquote":0.0,"Stichprobengr\u00f6\u00dfe":4},{"Zug":"ICE 292","Fahrzeit inkl. Versp\u00e4tungen [min]":89.0,"Versp\u00e4tung Abfahrt [min]":12.0,"Versp\u00e4tung Ankunft [min]":18.0,"Ausfallquote":0.0,"Stichprobengr\u00f6\u00dfe":2},{"Zug":"ICE 657","Fahrzeit inkl. Versp\u00e4tungen [min]":121.0,"Versp\u00e4tung Abfahrt [min]":8.0,"Versp\u00e4tung Ankunft [min]":-17.0,"Ausfallquote":0.0,"Stichprobengr\u00f6\u00dfe":2},{"Zug":"ICE 2524","Fahrzeit inkl. Versp\u00e4tungen [min]":78.0,"Versp\u00e4tung Abfahrt [min]":6.0,"Versp\u00e4tung Ankunft [min]":0.0,"Ausfallquote":0.0,"Stichprobengr\u00f6\u00dfe":1}]