[{"Zug":"ICE 100","Fahrzeit inkl. Versp\u00e4tungen [min]":108.2266666667,"Versp\u00e4tung Abfahrt [min]":33.0,"Versp\u00e4tung Ankunft [min]":32.1333333333,"Ausfallquote":0.1573033708,"Stichprobengr\u00f6\u00dfe":89},{"Zug":"IC 2431","Fahrzeit inkl. Versp\u00e4tungen [min]":111.9807692308,"Versp\u00e4tung Abfahrt [min]":13.4038461538,"Versp\u00e4tung Ankunft [min]":16.3846153846,"Ausfallquote":0.223880597,"Stichprobengr\u00f6\u00dfe":67},{"Zug":"IC 2035","Fahrzeit inkl. Versp\u00e4tungen [min]":105.0,"Versp\u00e4tung Abfahrt [min]":4.0,"Versp\u00e4tung Ankunft [min]":-1.0,"Ausfallquote":0.0,"Stichprobengr\u00f6\u00dfe":1}]