[{"Zug":"RE 68","Fahrzeit inkl. Versp\u00e4tungen [min]":52.7728911319,"Versp\u00e4tung Abfahrt [min]":2.8233597693,"Versp\u00e4tung Ankunft [min]":3.7217015141,"Ausfallquote":0.0414651002,"Stichprobengr\u00f6\u00dfe":1447},{"Zug":"FLX 10","Fahrzeit inkl. Versp\u00e4tungen [min]":34.325,"Versp\u00e4tung Abfahrt [min]":27.0,"Versp\u00e4tung Ankunft [min]":20.3,"Ausfallquote":0.043062201,"Stichprobengr\u00f6\u00dfe":209},{"Zug":"ICE 2401","Fahrzeit inkl. Versp\u00e4tungen [min]":35.9240506329,"Versp\u00e4tung Abfahrt [min]":11.5063291139,"Versp\u00e4tung Ankunft [min]":1.9240506329,"Ausfallquote":0.1318681319,"Stichprobengr\u00f6\u00dfe":91},{"Zug":"ICE 2407","Fahrzeit inkl. Versp\u00e4tungen [min]":35.5609756098,"Versp\u00e4tung Abfahrt [min]":16.8536585366,"Versp\u00e4tung Ankunft [min]":6.4146341463,"Ausfallquote":0.0989010989,"Stichprobengr\u00f6\u00dfe":91},{"Zug":"ICE 717","Fahrzeit inkl. Versp\u00e4tungen [min]":43.5287356322,"Versp\u00e4tung Abfahrt [min]":1.1609195402,"Versp\u00e4tung Ankunft [min]":-1.3103448276,"Ausfallquote":0.043956044,"Stichprobengr\u00f6\u00dfe":91},{"Zug":"NJ","Fahrzeit inkl. Versp\u00e4tungen [min]":36.2823529412,"Versp\u00e4tung Abfahrt [min]":13.8941176471,"Versp\u00e4tung Ankunft [min]":8.4941176471,"Ausfallquote":0.0555555556,"Stichprobengr\u00f6\u00dfe":90},{"Zug":"IC 60471","Fahrzeit inkl. Versp\u00e4tungen [min]":36.9058823529,"Versp\u00e4tung Abfahrt [min]":13.7294117647,"Versp\u00e4tung Ankunft [min]":8.9529411765,"Ausfallquote":0.0555555556,"Stichprobengr\u00f6\u00dfe":90},{"Zug":"ICE 2409","Fahrzeit inkl. Versp\u00e4tungen [min]":35.7469879518,"Versp\u00e4tung Abfahrt [min]":21.9036144578,"Versp\u00e4tung Ankunft [min]":11.6506024096,"Ausfallquote":0.0777777778,"Stichprobengr\u00f6\u00dfe":90},{"Zug":"ICE 2403","Fahrzeit inkl. Versp\u00e4tungen [min]":37.2658227848,"Versp\u00e4tung Abfahrt [min]":10.8734177215,"Versp\u00e4tung Ankunft [min]":2.1392405063,"Ausfallquote":0.1123595506,"Stichprobengr\u00f6\u00dfe":89},{"Zug":"ICE 2415","Fahrzeit inkl. Versp\u00e4tungen [min]":34.7023809524,"Versp\u00e4tung Abfahrt [min]":33.0833333333,"Versp\u00e4tung Ankunft [min]":22.130952381,"Ausfallquote":0.0454545455,"Stichprobengr\u00f6\u00dfe":88},{"Zug":"ICE 699","Fahrzeit inkl. Versp\u00e4tungen [min]":36.8214285714,"Versp\u00e4tung Abfahrt [min]":17.2619047619,"Versp\u00e4tung Ankunft [min]":6.7976190476,"Ausfallquote":0.0454545455,"Stichprobengr\u00f6\u00dfe":88},{"Zug":"ICE 2405","Fahrzeit inkl. Versp\u00e4tungen [min]":36.1794871795,"Versp\u00e4tung Abfahrt [min]":13.7179487179,"Versp\u00e4tung Ankunft [min]":3.8974358974,"Ausfallquote":0.0930232558,"Stichprobengr\u00f6\u00dfe":86},{"Zug":"ICE 2413","Fahrzeit inkl. Versp\u00e4tungen [min]":37.4578313253,"Versp\u00e4tung Abfahrt [min]":22.6506024096,"Versp\u00e4tung Ankunft [min]":14.1084337349,"Ausfallquote":0.0348837209,"Stichprobengr\u00f6\u00dfe":86},{"Zug":"ICE 697","Fahrzeit inkl. Versp\u00e4tungen [min]":35.641025641,"Versp\u00e4tung Abfahrt [min]":26.641025641,"Versp\u00e4tung Ankunft [min]":14.6538461538,"Ausfallquote":0.0823529412,"Stichprobengr\u00f6\u00dfe":85},{"Zug":"ICE 773","Fahrzeit inkl. Versp\u00e4tungen [min]":56.9358974359,"Versp\u00e4tung Abfahrt [min]":25.8076923077,"Versp\u00e4tung Ankunft [min]":22.5512820513,"Ausfallquote":0.037037037,"Stichprobengr\u00f6\u00dfe":81},{"Zug":"ICE 1511","Fahrzeit inkl. Versp\u00e4tungen [min]":46.02,"Versp\u00e4tung Abfahrt [min]":2.62,"Versp\u00e4tung Ankunft [min]":-5.36,"Ausfallquote":0.358974359,"Stichprobengr\u00f6\u00dfe":78},{"Zug":"ICE 2411","Fahrzeit inkl. Versp\u00e4tungen [min]":34.875,"Versp\u00e4tung Abfahrt [min]":25.2361111111,"Versp\u00e4tung Ankunft [min]":14.1111111111,"Ausfallquote":0.027027027,"Stichprobengr\u00f6\u00dfe":74},{"Zug":"IC 2381","Fahrzeit inkl. Versp\u00e4tungen [min]":46.9285714286,"Versp\u00e4tung Abfahrt [min]":1.4821428571,"Versp\u00e4tung Ankunft [min]":-0.5892857143,"Ausfallquote":0.1111111111,"Stichprobengr\u00f6\u00dfe":63},{"Zug":"Bus RE60","Fahrzeit inkl. Versp\u00e4tungen [min]":151.7142857143,"Versp\u00e4tung Abfahrt [min]":3.4285714286,"Versp\u00e4tung Ankunft [min]":20.7142857143,"Ausfallquote":0.0,"Stichprobengr\u00f6\u00dfe":7},{"Zug":"ICE 2503","Fahrzeit inkl. Versp\u00e4tungen [min]":53.5,"Versp\u00e4tung Abfahrt [min]":25.5,"Versp\u00e4tung Ankunft [min]":19.0,"Ausfallquote":0.0,"Stichprobengr\u00f6\u00dfe":2},{"Zug":"ICE 377","Fahrzeit inkl. Versp\u00e4tungen [min]":57.0,"Versp\u00e4tung Abfahrt [min]":8.0,"Versp\u00e4tung Ankunft [min]":34.0,"Ausfallquote":0.0,"Stichprobengr\u00f6\u00dfe":1},{"Zug":"DBK","Fahrzeit inkl. Versp\u00e4tungen [min]":44.0,"Versp\u00e4tung Abfahrt [min]":44.0,"Versp\u00e4tung Ankunft [min]":36.0,"Ausfallquote":0.0,"Stichprobengr\u00f6\u00dfe":1},{"Zug":"ICE 877","Fahrzeit inkl. Versp\u00e4tungen [min]":64.0,"Versp\u00e4tung Abfahrt [min]":10.0,"Versp\u00e4tung Ankunft [min]":-3.0,"Ausfallquote":0.0,"Stichprobengr\u00f6\u00dfe":1}]