[{"Zug":"RE 11","Fahrzeit inkl. Versp\u00e4tungen [min]":187.8638888889,"Versp\u00e4tung Abfahrt [min]":4.475,"Versp\u00e4tung Ankunft [min]":10.7472222222,"Ausfallquote":0.1818181818,"Stichprobengr\u00f6\u00dfe":440},{"Zug":"IC 2155","Fahrzeit inkl. Versp\u00e4tungen [min]":181.5647058824,"Versp\u00e4tung Abfahrt [min]":5.9529411765,"Versp\u00e4tung Ankunft [min]":14.5411764706,"Ausfallquote":0.0555555556,"Stichprobengr\u00f6\u00dfe":90},{"Zug":"IC 2157","Fahrzeit inkl. Versp\u00e4tungen [min]":181.5060240964,"Versp\u00e4tung Abfahrt [min]":9.0361445783,"Versp\u00e4tung Ankunft [min]":15.5421686747,"Ausfallquote":0.0674157303,"Stichprobengr\u00f6\u00dfe":89},{"Zug":"ICE 1223","Fahrzeit inkl. Versp\u00e4tungen [min]":186.2413793103,"Versp\u00e4tung Abfahrt [min]":9.8448275862,"Versp\u00e4tung Ankunft [min]":22.8793103448,"Ausfallquote":0.0333333333,"Stichprobengr\u00f6\u00dfe":60},{"Zug":"IC 1959","Fahrzeit inkl. Versp\u00e4tungen [min]":172.0666666667,"Versp\u00e4tung Abfahrt [min]":6.4,"Versp\u00e4tung Ankunft [min]":14.4,"Ausfallquote":0.2857142857,"Stichprobengr\u00f6\u00dfe":21}]