[{"Zug":"RE 6","Fahrzeit inkl. Versp\u00e4tungen [min]":52.6284987277,"Versp\u00e4tung Abfahrt [min]":9.187446989,"Versp\u00e4tung Ankunft [min]":10.9075487701,"Ausfallquote":0.1362637363,"Stichprobengr\u00f6\u00dfe":1365},{"Zug":"FLX 30","Fahrzeit inkl. Versp\u00e4tungen [min]":43.8474576271,"Versp\u00e4tung Abfahrt [min]":27.3389830508,"Versp\u00e4tung Ankunft [min]":33.0,"Ausfallquote":0.078125,"Stichprobengr\u00f6\u00dfe":64},{"Zug":"ICE 846","Fahrzeit inkl. Versp\u00e4tungen [min]":51.6923076923,"Versp\u00e4tung Abfahrt [min]":19.3076923077,"Versp\u00e4tung Ankunft [min]":22.1538461538,"Ausfallquote":0.4347826087,"Stichprobengr\u00f6\u00dfe":23},{"Zug":"TRI RE6","Fahrzeit inkl. Versp\u00e4tungen [min]":51.4,"Versp\u00e4tung Abfahrt [min]":4.6,"Versp\u00e4tung Ankunft [min]":9.2,"Ausfallquote":0.1666666667,"Stichprobengr\u00f6\u00dfe":6},{"Zug":"RE 1","Fahrzeit inkl. Versp\u00e4tungen [min]":48.0,"Versp\u00e4tung Abfahrt [min]":8.0,"Versp\u00e4tung Ankunft [min]":6.0,"Ausfallquote":0.5,"Stichprobengr\u00f6\u00dfe":4}]