[{"Zug":"ICE 794","Fahrzeit inkl. Versp\u00e4tungen [min]":163.6037735849,"Versp\u00e4tung Abfahrt [min]":10.320754717,"Versp\u00e4tung Ankunft [min]":19.2075471698,"Ausfallquote":0.1166666667,"Stichprobengr\u00f6\u00dfe":60},{"Zug":"ICE 994","Fahrzeit inkl. Versp\u00e4tungen [min]":162.5,"Versp\u00e4tung Abfahrt [min]":4.2,"Versp\u00e4tung Ankunft [min]":10.94,"Ausfallquote":0.0740740741,"Stichprobengr\u00f6\u00dfe":54},{"Zug":"ICE 276","Fahrzeit inkl. Versp\u00e4tungen [min]":157.3404255319,"Versp\u00e4tung Abfahrt [min]":20.8723404255,"Versp\u00e4tung Ankunft [min]":14.7446808511,"Ausfallquote":0.1132075472,"Stichprobengr\u00f6\u00dfe":53},{"Zug":"ICE 796","Fahrzeit inkl. Versp\u00e4tungen [min]":163.8979591837,"Versp\u00e4tung Abfahrt [min]":6.1632653061,"Versp\u00e4tung Ankunft [min]":12.8979591837,"Ausfallquote":0.0754716981,"Stichprobengr\u00f6\u00dfe":53},{"Zug":"ICE 798","Fahrzeit inkl. Versp\u00e4tungen [min]":160.1,"Versp\u00e4tung Abfahrt [min]":6.24,"Versp\u00e4tung Ankunft [min]":13.34,"Ausfallquote":0.0566037736,"Stichprobengr\u00f6\u00dfe":53},{"Zug":"ICE 992","Fahrzeit inkl. Versp\u00e4tungen [min]":161.387755102,"Versp\u00e4tung Abfahrt [min]":4.8979591837,"Versp\u00e4tung Ankunft [min]":9.2857142857,"Ausfallquote":0.0576923077,"Stichprobengr\u00f6\u00dfe":52},{"Zug":"ICE 996","Fahrzeit inkl. Versp\u00e4tungen [min]":159.3170731707,"Versp\u00e4tung Abfahrt [min]":1.2926829268,"Versp\u00e4tung Ankunft [min]":8.6097560976,"Ausfallquote":0.0681818182,"Stichprobengr\u00f6\u00dfe":44},{"Zug":"ICE 274","Fahrzeit inkl. Versp\u00e4tungen [min]":148.3333333333,"Versp\u00e4tung Abfahrt [min]":13.6666666667,"Versp\u00e4tung Ankunft [min]":4.6666666667,"Ausfallquote":0.25,"Stichprobengr\u00f6\u00dfe":4},{"Zug":"ICE 2524","Fahrzeit inkl. Versp\u00e4tungen [min]":153.0,"Versp\u00e4tung Abfahrt [min]":0.0,"Versp\u00e4tung Ankunft [min]":0.0,"Ausfallquote":0.0,"Stichprobengr\u00f6\u00dfe":1},{"Zug":"ICE 2526","Fahrzeit inkl. Versp\u00e4tungen [min]":148.0,"Versp\u00e4tung Abfahrt [min]":16.0,"Versp\u00e4tung Ankunft [min]":7.0,"Ausfallquote":0.0,"Stichprobengr\u00f6\u00dfe":1},{"Zug":"ICE 2548","Fahrzeit inkl. Versp\u00e4tungen [min]":150.0,"Versp\u00e4tung Abfahrt [min]":6.0,"Versp\u00e4tung Ankunft [min]":3.0,"Ausfallquote":0.0,"Stichprobengr\u00f6\u00dfe":1},{"Zug":"ICE 2572","Fahrzeit inkl. Versp\u00e4tungen [min]":170.0,"Versp\u00e4tung Abfahrt [min]":7.0,"Versp\u00e4tung Ankunft [min]":20.0,"Ausfallquote":0.0,"Stichprobengr\u00f6\u00dfe":1}]