[{"Zug":"IC 2040","Fahrzeit inkl. Versp\u00e4tungen [min]":216.1627906977,"Versp\u00e4tung Abfahrt [min]":7.5,"Versp\u00e4tung Ankunft [min]":18.2325581395,"Ausfallquote":0.0444444444,"Stichprobengr\u00f6\u00dfe":90},{"Zug":"ICE 613","Fahrzeit inkl. Versp\u00e4tungen [min]":159.9397590361,"Versp\u00e4tung Abfahrt [min]":14.1686746988,"Versp\u00e4tung Ankunft [min]":29.1325301205,"Ausfallquote":0.0777777778,"Stichprobengr\u00f6\u00dfe":90},{"Zug":"ICE 615","Fahrzeit inkl. Versp\u00e4tungen [min]":157.0117647059,"Versp\u00e4tung Abfahrt [min]":15.9764705882,"Versp\u00e4tung Ankunft [min]":25.8941176471,"Ausfallquote":0.0555555556,"Stichprobengr\u00f6\u00dfe":90},{"Zug":"ICE 103","Fahrzeit inkl. Versp\u00e4tungen [min]":151.9879518072,"Versp\u00e4tung Abfahrt [min]":9.1084337349,"Versp\u00e4tung Ankunft [min]":16.1686746988,"Ausfallquote":0.0674157303,"Stichprobengr\u00f6\u00dfe":89},{"Zug":"ICE 515","Fahrzeit inkl. Versp\u00e4tungen [min]":155.0117647059,"Versp\u00e4tung Abfahrt [min]":10.0705882353,"Versp\u00e4tung Ankunft [min]":20.1058823529,"Ausfallquote":0.0449438202,"Stichprobengr\u00f6\u00dfe":89},{"Zug":"ICE 517","Fahrzeit inkl. Versp\u00e4tungen [min]":152.6419753086,"Versp\u00e4tung Abfahrt [min]":17.8271604938,"Versp\u00e4tung Ankunft [min]":25.4938271605,"Ausfallquote":0.0898876404,"Stichprobengr\u00f6\u00dfe":89},{"Zug":"ICE 611","Fahrzeit inkl. Versp\u00e4tungen [min]":158.25,"Versp\u00e4tung Abfahrt [min]":13.4642857143,"Versp\u00e4tung Ankunft [min]":26.7380952381,"Ausfallquote":0.0561797753,"Stichprobengr\u00f6\u00dfe":89},{"Zug":"ICE 119","Fahrzeit inkl. Versp\u00e4tungen [min]":217.3,"Versp\u00e4tung Abfahrt [min]":0.325,"Versp\u00e4tung Ankunft [min]":3.725,"Ausfallquote":0.0,"Stichprobengr\u00f6\u00dfe":80},{"Zug":"IC 2046","Fahrzeit inkl. Versp\u00e4tungen [min]":224.4444444444,"Versp\u00e4tung Abfahrt [min]":7.2962962963,"Versp\u00e4tung Ankunft [min]":24.537037037,"Ausfallquote":0.1,"Stichprobengr\u00f6\u00dfe":60},{"Zug":"IC 2048","Fahrzeit inkl. Versp\u00e4tungen [min]":221.7857142857,"Versp\u00e4tung Abfahrt [min]":13.0178571429,"Versp\u00e4tung Ankunft [min]":28.9642857143,"Ausfallquote":0.0666666667,"Stichprobengr\u00f6\u00dfe":60},{"Zug":"IC 2440","Fahrzeit inkl. Versp\u00e4tungen [min]":227.6170212766,"Versp\u00e4tung Abfahrt [min]":11.3404255319,"Versp\u00e4tung Ankunft [min]":33.2978723404,"Ausfallquote":0.2166666667,"Stichprobengr\u00f6\u00dfe":60},{"Zug":"ICE 1944","Fahrzeit inkl. Versp\u00e4tungen [min]":224.8363636364,"Versp\u00e4tung Abfahrt [min]":10.1272727273,"Versp\u00e4tung Ankunft [min]":30.4909090909,"Ausfallquote":0.0677966102,"Stichprobengr\u00f6\u00dfe":59},{"Zug":"ICE 205","Fahrzeit inkl. Versp\u00e4tungen [min]":160.1346153846,"Versp\u00e4tung Abfahrt [min]":18.9230769231,"Versp\u00e4tung Ankunft [min]":25.6923076923,"Ausfallquote":0.0545454545,"Stichprobengr\u00f6\u00dfe":55},{"Zug":"ICE 519","Fahrzeit inkl. Versp\u00e4tungen [min]":152.7931034483,"Versp\u00e4tung Abfahrt [min]":17.1034482759,"Versp\u00e4tung Ankunft [min]":23.8965517241,"Ausfallquote":0.064516129,"Stichprobengr\u00f6\u00dfe":31}]