[{"Zug":"S 6","Fahrzeit inkl. Versp\u00e4tungen [min]":48.3702432938,"Versp\u00e4tung Abfahrt [min]":2.9029943855,"Versp\u00e4tung Ankunft [min]":3.0383655646,"Ausfallquote":0.0486646884,"Stichprobengr\u00f6\u00dfe":3370},{"Zug":"S 11","Fahrzeit inkl. Versp\u00e4tungen [min]":71.5696202532,"Versp\u00e4tung Abfahrt [min]":3.418872267,"Versp\u00e4tung Ankunft [min]":4.1442270809,"Ausfallquote":0.1633504493,"Stichprobengr\u00f6\u00dfe":3116},{"Zug":"RE 1","Fahrzeit inkl. Versp\u00e4tungen [min]":30.2661904762,"Versp\u00e4tung Abfahrt [min]":6.6585714286,"Versp\u00e4tung Ankunft [min]":9.0576190476,"Ausfallquote":0.0480507706,"Stichprobengr\u00f6\u00dfe":2206},{"Zug":"RE 5","Fahrzeit inkl. Versp\u00e4tungen [min]":28.6053611318,"Versp\u00e4tung Abfahrt [min]":8.0878629933,"Versp\u00e4tung Ankunft [min]":9.6947133284,"Ausfallquote":0.0832764505,"Stichprobengr\u00f6\u00dfe":1465},{"Zug":"RE 6","Fahrzeit inkl. Versp\u00e4tungen [min]":38.5317073171,"Versp\u00e4tung Abfahrt [min]":4.6975609756,"Versp\u00e4tung Ankunft [min]":8.3073170732,"Ausfallquote":0.0888888889,"Stichprobengr\u00f6\u00dfe":225},{"Zug":"ICE 726","Fahrzeit inkl. Versp\u00e4tungen [min]":21.2771084337,"Versp\u00e4tung Abfahrt [min]":11.6987951807,"Versp\u00e4tung Ankunft [min]":12.9518072289,"Ausfallquote":0.0459770115,"Stichprobengr\u00f6\u00dfe":87},{"Zug":"ICE 628","Fahrzeit inkl. Versp\u00e4tungen [min]":23.6962025316,"Versp\u00e4tung Abfahrt [min]":10.2278481013,"Versp\u00e4tung Ankunft [min]":13.0,"Ausfallquote":0.091954023,"Stichprobengr\u00f6\u00dfe":87},{"Zug":"ICE 728","Fahrzeit inkl. Versp\u00e4tungen [min]":22.3012048193,"Versp\u00e4tung Abfahrt [min]":8.8313253012,"Versp\u00e4tung Ankunft [min]":10.8674698795,"Ausfallquote":0.0459770115,"Stichprobengr\u00f6\u00dfe":87},{"Zug":"ICE 622","Fahrzeit inkl. Versp\u00e4tungen [min]":21.5584415584,"Versp\u00e4tung Abfahrt [min]":19.5584415584,"Versp\u00e4tung Ankunft [min]":19.8571428571,"Ausfallquote":0.1149425287,"Stichprobengr\u00f6\u00dfe":87},{"Zug":"ICE 624","Fahrzeit inkl. Versp\u00e4tungen [min]":22.7037037037,"Versp\u00e4tung Abfahrt [min]":19.2839506173,"Versp\u00e4tung Ankunft [min]":22.6049382716,"Ausfallquote":0.0689655172,"Stichprobengr\u00f6\u00dfe":87},{"Zug":"ICE 626","Fahrzeit inkl. Versp\u00e4tungen [min]":22.6075949367,"Versp\u00e4tung Abfahrt [min]":18.3544303797,"Versp\u00e4tung Ankunft [min]":21.5949367089,"Ausfallquote":0.091954023,"Stichprobengr\u00f6\u00dfe":87},{"Zug":"ICE 720","Fahrzeit inkl. Versp\u00e4tungen [min]":23.0675675676,"Versp\u00e4tung Abfahrt [min]":8.9324324324,"Versp\u00e4tung Ankunft [min]":11.7027027027,"Ausfallquote":0.1494252874,"Stichprobengr\u00f6\u00dfe":87},{"Zug":"ICE 722","Fahrzeit inkl. Versp\u00e4tungen [min]":23.1025641026,"Versp\u00e4tung Abfahrt [min]":13.141025641,"Versp\u00e4tung Ankunft [min]":15.0897435897,"Ausfallquote":0.1034482759,"Stichprobengr\u00f6\u00dfe":87},{"Zug":"ICE 724","Fahrzeit inkl. Versp\u00e4tungen [min]":22.8289473684,"Versp\u00e4tung Abfahrt [min]":10.1842105263,"Versp\u00e4tung Ankunft [min]":13.4605263158,"Ausfallquote":0.1264367816,"Stichprobengr\u00f6\u00dfe":87},{"Zug":"ICE 524","Fahrzeit inkl. Versp\u00e4tungen [min]":22.1184210526,"Versp\u00e4tung Abfahrt [min]":17.3289473684,"Versp\u00e4tung Ankunft [min]":19.6447368421,"Ausfallquote":0.0731707317,"Stichprobengr\u00f6\u00dfe":82},{"Zug":"ICE 822","Fahrzeit inkl. Versp\u00e4tungen [min]":22.2666666667,"Versp\u00e4tung Abfahrt [min]":9.6533333333,"Versp\u00e4tung Ankunft [min]":12.4933333333,"Ausfallquote":0.0740740741,"Stichprobengr\u00f6\u00dfe":81},{"Zug":"ICE 528","Fahrzeit inkl. Versp\u00e4tungen [min]":22.4342105263,"Versp\u00e4tung Abfahrt [min]":21.8684210526,"Versp\u00e4tung Ankunft [min]":24.1710526316,"Ausfallquote":0.0617283951,"Stichprobengr\u00f6\u00dfe":81},{"Zug":"ICE 526","Fahrzeit inkl. Versp\u00e4tungen [min]":21.88,"Versp\u00e4tung Abfahrt [min]":25.92,"Versp\u00e4tung Ankunft [min]":28.0,"Ausfallquote":0.0506329114,"Stichprobengr\u00f6\u00dfe":79},{"Zug":"NJ","Fahrzeit inkl. Versp\u00e4tungen [min]":32.7352941176,"Versp\u00e4tung Abfahrt [min]":37.7647058824,"Versp\u00e4tung Ankunft [min]":46.0882352941,"Ausfallquote":0.1168831169,"Stichprobengr\u00f6\u00dfe":77},{"Zug":"ICE 820","Fahrzeit inkl. Versp\u00e4tungen [min]":21.3880597015,"Versp\u00e4tung Abfahrt [min]":9.6865671642,"Versp\u00e4tung Ankunft [min]":11.2985074627,"Ausfallquote":0.0694444444,"Stichprobengr\u00f6\u00dfe":72},{"Zug":"ICE 824","Fahrzeit inkl. Versp\u00e4tungen [min]":23.0447761194,"Versp\u00e4tung Abfahrt [min]":4.7164179104,"Versp\u00e4tung Ankunft [min]":4.8955223881,"Ausfallquote":0.0694444444,"Stichprobengr\u00f6\u00dfe":72},{"Zug":"ICE 518","Fahrzeit inkl. Versp\u00e4tungen [min]":24.7575757576,"Versp\u00e4tung Abfahrt [min]":8.6212121212,"Versp\u00e4tung Ankunft [min]":10.8333333333,"Ausfallquote":0.0571428571,"Stichprobengr\u00f6\u00dfe":70},{"Zug":"ICE 200","Fahrzeit inkl. Versp\u00e4tungen [min]":25.78125,"Versp\u00e4tung Abfahrt [min]":7.75,"Versp\u00e4tung Ankunft [min]":-1.71875,"Ausfallquote":0.0857142857,"Stichprobengr\u00f6\u00dfe":70},{"Zug":"ICE 206","Fahrzeit inkl. Versp\u00e4tungen [min]":24.9692307692,"Versp\u00e4tung Abfahrt [min]":6.0307692308,"Versp\u00e4tung Ankunft [min]":5.0,"Ausfallquote":0.0714285714,"Stichprobengr\u00f6\u00dfe":70},{"Zug":"ICE 620","Fahrzeit inkl. Versp\u00e4tungen [min]":24.2786885246,"Versp\u00e4tung Abfahrt [min]":24.6885245902,"Versp\u00e4tung Ankunft [min]":28.3278688525,"Ausfallquote":0.115942029,"Stichprobengr\u00f6\u00dfe":69},{"Zug":"ICE 120","Fahrzeit inkl. Versp\u00e4tungen [min]":23.375,"Versp\u00e4tung Abfahrt [min]":6.078125,"Versp\u00e4tung Ankunft [min]":10.234375,"Ausfallquote":0.0588235294,"Stichprobengr\u00f6\u00dfe":68},{"Zug":"ICE 102","Fahrzeit inkl. Versp\u00e4tungen [min]":23.84375,"Versp\u00e4tung Abfahrt [min]":10.4375,"Versp\u00e4tung Ankunft [min]":13.609375,"Ausfallquote":0.0588235294,"Stichprobengr\u00f6\u00dfe":68},{"Zug":"ICE 1028","Fahrzeit inkl. Versp\u00e4tungen [min]":22.5344827586,"Versp\u00e4tung Abfahrt [min]":1.3620689655,"Versp\u00e4tung Ankunft [min]":3.5517241379,"Ausfallquote":0.0,"Stichprobengr\u00f6\u00dfe":58},{"Zug":"ICE 1223","Fahrzeit inkl. Versp\u00e4tungen [min]":23.0784313725,"Versp\u00e4tung Abfahrt [min]":5.2941176471,"Versp\u00e4tung Ankunft [min]":7.137254902,"Ausfallquote":0.1052631579,"Stichprobengr\u00f6\u00dfe":57},{"Zug":"ICE 224","Fahrzeit inkl. Versp\u00e4tungen [min]":21.7659574468,"Versp\u00e4tung Abfahrt [min]":9.0638297872,"Versp\u00e4tung Ankunft [min]":9.7872340426,"Ausfallquote":0.1296296296,"Stichprobengr\u00f6\u00dfe":54},{"Zug":"ICE 124","Fahrzeit inkl. Versp\u00e4tungen [min]":23.7105263158,"Versp\u00e4tung Abfahrt [min]":6.2894736842,"Versp\u00e4tung Ankunft [min]":11.0,"Ausfallquote":0.1555555556,"Stichprobengr\u00f6\u00dfe":45},{"Zug":"ICE 128","Fahrzeit inkl. Versp\u00e4tungen [min]":21.5277777778,"Versp\u00e4tung Abfahrt [min]":4.5277777778,"Versp\u00e4tung Ankunft [min]":7.0555555556,"Ausfallquote":0.1,"Stichprobengr\u00f6\u00dfe":40},{"Zug":"ICE 220","Fahrzeit inkl. Versp\u00e4tungen [min]":21.2368421053,"Versp\u00e4tung Abfahrt [min]":3.9736842105,"Versp\u00e4tung Ankunft [min]":6.2105263158,"Ausfallquote":0.05,"Stichprobengr\u00f6\u00dfe":40},{"Zug":"ICE 126","Fahrzeit inkl. Versp\u00e4tungen [min]":21.65625,"Versp\u00e4tung Abfahrt [min]":2.5,"Versp\u00e4tung Ankunft [min]":5.15625,"Ausfallquote":0.2,"Stichprobengr\u00f6\u00dfe":40},{"Zug":"ICE 22","Fahrzeit inkl. Versp\u00e4tungen [min]":19.8076923077,"Versp\u00e4tung Abfahrt [min]":33.6538461538,"Versp\u00e4tung Ankunft [min]":35.1153846154,"Ausfallquote":0.2972972973,"Stichprobengr\u00f6\u00dfe":37},{"Zug":"ICE 920","Fahrzeit inkl. Versp\u00e4tungen [min]":20.0333333333,"Versp\u00e4tung Abfahrt [min]":8.8333333333,"Versp\u00e4tung Ankunft [min]":8.7666666667,"Ausfallquote":0.1428571429,"Stichprobengr\u00f6\u00dfe":35},{"Zug":"ICE 26","Fahrzeit inkl. Versp\u00e4tungen [min]":20.2962962963,"Versp\u00e4tung Abfahrt [min]":31.2222222222,"Versp\u00e4tung Ankunft [min]":32.6296296296,"Ausfallquote":0.2058823529,"Stichprobengr\u00f6\u00dfe":34},{"Zug":"ICE 222","Fahrzeit inkl. Versp\u00e4tungen [min]":21.8333333333,"Versp\u00e4tung Abfahrt [min]":2.9333333333,"Versp\u00e4tung Ankunft [min]":2.7666666667,"Ausfallquote":0.0322580645,"Stichprobengr\u00f6\u00dfe":31},{"Zug":"ICE 928","Fahrzeit inkl. Versp\u00e4tungen [min]":20.0357142857,"Versp\u00e4tung Abfahrt [min]":17.7857142857,"Versp\u00e4tung Ankunft [min]":19.3928571429,"Ausfallquote":0.0344827586,"Stichprobengr\u00f6\u00dfe":29},{"Zug":"ICE 28","Fahrzeit inkl. Versp\u00e4tungen [min]":21.2307692308,"Versp\u00e4tung Abfahrt [min]":17.8461538462,"Versp\u00e4tung Ankunft [min]":19.8846153846,"Ausfallquote":0.1034482759,"Stichprobengr\u00f6\u00dfe":29},{"Zug":"ICE 1020","Fahrzeit inkl. Versp\u00e4tungen [min]":21.4166666667,"Versp\u00e4tung Abfahrt [min]":19.3333333333,"Versp\u00e4tung Ankunft [min]":22.375,"Ausfallquote":0.0769230769,"Stichprobengr\u00f6\u00dfe":26},{"Zug":"TRI RE1","Fahrzeit inkl. Versp\u00e4tungen [min]":29.65,"Versp\u00e4tung Abfahrt [min]":7.9,"Versp\u00e4tung Ankunft [min]":7.5,"Ausfallquote":0.0,"Stichprobengr\u00f6\u00dfe":20},{"Zug":"ICE 118","Fahrzeit inkl. Versp\u00e4tungen [min]":19.6470588235,"Versp\u00e4tung Abfahrt [min]":7.2352941176,"Versp\u00e4tung Ankunft [min]":6.8823529412,"Ausfallquote":0.0,"Stichprobengr\u00f6\u00dfe":17},{"Zug":"ICE 914","Fahrzeit inkl. Versp\u00e4tungen [min]":20.1764705882,"Versp\u00e4tung Abfahrt [min]":7.5294117647,"Versp\u00e4tung Ankunft [min]":5.7058823529,"Ausfallquote":0.0,"Stichprobengr\u00f6\u00dfe":17},{"Zug":"ICE 918","Fahrzeit inkl. Versp\u00e4tungen [min]":20.8235294118,"Versp\u00e4tung Abfahrt [min]":12.1764705882,"Versp\u00e4tung Ankunft [min]":13.0,"Ausfallquote":0.0,"Stichprobengr\u00f6\u00dfe":17},{"Zug":"ICE 1022","Fahrzeit inkl. Versp\u00e4tungen [min]":20.2,"Versp\u00e4tung Abfahrt [min]":23.4666666667,"Versp\u00e4tung Ankunft [min]":24.4666666667,"Ausfallquote":0.1176470588,"Stichprobengr\u00f6\u00dfe":17},{"Zug":"ICE 1010","Fahrzeit inkl. Versp\u00e4tungen [min]":20.9411764706,"Versp\u00e4tung Abfahrt [min]":20.0588235294,"Versp\u00e4tung Ankunft [min]":20.0,"Ausfallquote":0.0,"Stichprobengr\u00f6\u00dfe":17},{"Zug":"ICE 114","Fahrzeit inkl. Versp\u00e4tungen [min]":24.1176470588,"Versp\u00e4tung Abfahrt [min]":2.1764705882,"Versp\u00e4tung Ankunft [min]":4.2941176471,"Ausfallquote":0.0,"Stichprobengr\u00f6\u00dfe":17},{"Zug":"ICE 912","Fahrzeit inkl. Versp\u00e4tungen [min]":20.6428571429,"Versp\u00e4tung Abfahrt [min]":19.3571428571,"Versp\u00e4tung Ankunft [min]":21.0,"Ausfallquote":0.125,"Stichprobengr\u00f6\u00dfe":16},{"Zug":"ICE 910","Fahrzeit inkl. Versp\u00e4tungen [min]":18.2666666667,"Versp\u00e4tung Abfahrt [min]":11.2666666667,"Versp\u00e4tung Ankunft [min]":8.5333333333,"Ausfallquote":0.0625,"Stichprobengr\u00f6\u00dfe":16},{"Zug":"ICE 2522","Fahrzeit inkl. Versp\u00e4tungen [min]":22.5,"Versp\u00e4tung Abfahrt [min]":32.5714285714,"Versp\u00e4tung Ankunft [min]":35.0714285714,"Ausfallquote":0.0666666667,"Stichprobengr\u00f6\u00dfe":15},{"Zug":"EC 8","Fahrzeit inkl. Versp\u00e4tungen [min]":22.5,"Versp\u00e4tung Abfahrt [min]":11.6666666667,"Versp\u00e4tung Ankunft [min]":15.1666666667,"Ausfallquote":0.1428571429,"Stichprobengr\u00f6\u00dfe":14},{"Zug":"IC 606","Fahrzeit inkl. Versp\u00e4tungen [min]":22.5,"Versp\u00e4tung Abfahrt [min]":8.5,"Versp\u00e4tung Ankunft [min]":9.5,"Ausfallquote":0.1428571429,"Stichprobengr\u00f6\u00dfe":14},{"Zug":"IC 2441","Fahrzeit inkl. Versp\u00e4tungen [min]":22.4545454545,"Versp\u00e4tung Abfahrt [min]":7.0909090909,"Versp\u00e4tung Ankunft [min]":9.5454545455,"Ausfallquote":0.2142857143,"Stichprobengr\u00f6\u00dfe":14},{"Zug":"IC 5107","Fahrzeit inkl. Versp\u00e4tungen [min]":27.25,"Versp\u00e4tung Abfahrt [min]":6.8333333333,"Versp\u00e4tung Ankunft [min]":10.5833333333,"Ausfallquote":0.1428571429,"Stichprobengr\u00f6\u00dfe":14},{"Zug":"IC 60402","Fahrzeit inkl. Versp\u00e4tungen [min]":26.9090909091,"Versp\u00e4tung Abfahrt [min]":24.2727272727,"Versp\u00e4tung Ankunft [min]":24.6363636364,"Ausfallquote":0.1538461538,"Stichprobengr\u00f6\u00dfe":13},{"Zug":"ICE 1120","Fahrzeit inkl. Versp\u00e4tungen [min]":19.7272727273,"Versp\u00e4tung Abfahrt [min]":32.1818181818,"Versp\u00e4tung Ankunft [min]":32.9090909091,"Ausfallquote":0.0833333333,"Stichprobengr\u00f6\u00dfe":12},{"Zug":"ICE 1012","Fahrzeit inkl. Versp\u00e4tungen [min]":20.4166666667,"Versp\u00e4tung Abfahrt [min]":5.75,"Versp\u00e4tung Ankunft [min]":6.1666666667,"Ausfallquote":0.0,"Stichprobengr\u00f6\u00dfe":12},{"Zug":"FLX 30","Fahrzeit inkl. Versp\u00e4tungen [min]":25.6666666667,"Versp\u00e4tung Abfahrt [min]":14.9166666667,"Versp\u00e4tung Ankunft [min]":21.1666666667,"Ausfallquote":0.0,"Stichprobengr\u00f6\u00dfe":12},{"Zug":"ICE 1014","Fahrzeit inkl. Versp\u00e4tungen [min]":21.2222222222,"Versp\u00e4tung Abfahrt [min]":5.3333333333,"Versp\u00e4tung Ankunft [min]":5.0,"Ausfallquote":0.0,"Stichprobengr\u00f6\u00dfe":9},{"Zug":"IC 2202","Fahrzeit inkl. Versp\u00e4tungen [min]":22.1428571429,"Versp\u00e4tung Abfahrt [min]":7.0,"Versp\u00e4tung Ankunft [min]":9.1428571429,"Ausfallquote":0.2222222222,"Stichprobengr\u00f6\u00dfe":9},{"Zug":"IC 2004","Fahrzeit inkl. Versp\u00e4tungen [min]":22.0,"Versp\u00e4tung Abfahrt [min]":8.4444444444,"Versp\u00e4tung Ankunft [min]":10.4444444444,"Ausfallquote":0.0,"Stichprobengr\u00f6\u00dfe":9},{"Zug":"ICE 1122","Fahrzeit inkl. Versp\u00e4tungen [min]":22.5714285714,"Versp\u00e4tung Abfahrt [min]":4.7142857143,"Versp\u00e4tung Ankunft [min]":1.2857142857,"Ausfallquote":0.125,"Stichprobengr\u00f6\u00dfe":8},{"Zug":"ICE 122","Fahrzeit inkl. Versp\u00e4tungen [min]":null,"Versp\u00e4tung Abfahrt [min]":null,"Versp\u00e4tung Ankunft [min]":null,"Ausfallquote":1.0,"Stichprobengr\u00f6\u00dfe":7},{"Zug":"TRI RE6","Fahrzeit inkl. Versp\u00e4tungen [min]":33.0,"Versp\u00e4tung Abfahrt [min]":9.1666666667,"Versp\u00e4tung Ankunft [min]":13.5,"Ausfallquote":0.0,"Stichprobengr\u00f6\u00dfe":6},{"Zug":"ICE 2402","Fahrzeit inkl. Versp\u00e4tungen [min]":27.75,"Versp\u00e4tung Abfahrt [min]":21.0,"Versp\u00e4tung Ankunft [min]":25.75,"Ausfallquote":0.2,"Stichprobengr\u00f6\u00dfe":5},{"Zug":"ICE 1902","Fahrzeit inkl. Versp\u00e4tungen [min]":28.8,"Versp\u00e4tung Abfahrt [min]":11.8,"Versp\u00e4tung Ankunft [min]":15.8,"Ausfallquote":0.0,"Stichprobengr\u00f6\u00dfe":5},{"Zug":"ICE 2400","Fahrzeit inkl. Versp\u00e4tungen [min]":27.0,"Versp\u00e4tung Abfahrt [min]":4.0,"Versp\u00e4tung Ankunft [min]":2.0,"Ausfallquote":0.0,"Stichprobengr\u00f6\u00dfe":3},{"Zug":"ICE 826","Fahrzeit inkl. Versp\u00e4tungen [min]":null,"Versp\u00e4tung Abfahrt [min]":null,"Versp\u00e4tung Ankunft [min]":null,"Ausfallquote":1.0,"Stichprobengr\u00f6\u00dfe":2},{"Zug":"TRI RE5","Fahrzeit inkl. Versp\u00e4tungen [min]":31.5,"Versp\u00e4tung Abfahrt [min]":35.5,"Versp\u00e4tung Ankunft [min]":34.0,"Ausfallquote":0.0,"Stichprobengr\u00f6\u00dfe":2},{"Zug":"MSM","Fahrzeit inkl. Versp\u00e4tungen [min]":25.0,"Versp\u00e4tung Abfahrt [min]":10.0,"Versp\u00e4tung Ankunft [min]":13.0,"Ausfallquote":0.0,"Stichprobengr\u00f6\u00dfe":1},{"Zug":"RB 48","Fahrzeit inkl. Versp\u00e4tungen [min]":30.0,"Versp\u00e4tung Abfahrt [min]":35.0,"Versp\u00e4tung Ankunft [min]":23.0,"Ausfallquote":0.0,"Stichprobengr\u00f6\u00dfe":1},{"Zug":"IC 2349","Fahrzeit inkl. Versp\u00e4tungen [min]":20.0,"Versp\u00e4tung Abfahrt [min]":22.0,"Versp\u00e4tung Ankunft [min]":23.0,"Ausfallquote":0.0,"Stichprobengr\u00f6\u00dfe":1},{"Zug":"UEX","Fahrzeit inkl. Versp\u00e4tungen [min]":23.0,"Versp\u00e4tung Abfahrt [min]":22.0,"Versp\u00e4tung Ankunft [min]":17.0,"Ausfallquote":0.0,"Stichprobengr\u00f6\u00dfe":1}]