[{"Zug":"ICE 77","Fahrzeit inkl. Versp\u00e4tungen [min]":196.380952381,"Versp\u00e4tung Abfahrt [min]":3.0476190476,"Versp\u00e4tung Ankunft [min]":16.3928571429,"Ausfallquote":0.0869565217,"Stichprobengr\u00f6\u00dfe":92},{"Zug":"ICE 1171","Fahrzeit inkl. Versp\u00e4tungen [min]":195.8701298701,"Versp\u00e4tung Abfahrt [min]":3.2597402597,"Versp\u00e4tung Ankunft [min]":16.1298701299,"Ausfallquote":0.0722891566,"Stichprobengr\u00f6\u00dfe":83},{"Zug":"ICE 885","Fahrzeit inkl. Versp\u00e4tungen [min]":214.6973684211,"Versp\u00e4tung Abfahrt [min]":4.5921052632,"Versp\u00e4tung Ankunft [min]":9.2894736842,"Ausfallquote":0.0843373494,"Stichprobengr\u00f6\u00dfe":83},{"Zug":"ICE 573","Fahrzeit inkl. Versp\u00e4tungen [min]":191.03125,"Versp\u00e4tung Abfahrt [min]":3.28125,"Versp\u00e4tung Ankunft [min]":11.3125,"Ausfallquote":0.0588235294,"Stichprobengr\u00f6\u00dfe":68},{"Zug":"ICE 73","Fahrzeit inkl. Versp\u00e4tungen [min]":195.3650793651,"Versp\u00e4tung Abfahrt [min]":2.1587301587,"Versp\u00e4tung Ankunft [min]":14.3333333333,"Ausfallquote":0.0454545455,"Stichprobengr\u00f6\u00dfe":66},{"Zug":"ICE 75","Fahrzeit inkl. Versp\u00e4tungen [min]":196.2307692308,"Versp\u00e4tung Abfahrt [min]":2.1923076923,"Versp\u00e4tung Ankunft [min]":12.2692307692,"Ausfallquote":0.0,"Stichprobengr\u00f6\u00dfe":26}]