[{"Zug":"RE 6","Fahrzeit inkl. Versp\u00e4tungen [min]":54.8409090909,"Versp\u00e4tung Abfahrt [min]":5.6420454545,"Versp\u00e4tung Ankunft [min]":8.5771103896,"Ausfallquote":0.060259344,"Stichprobengr\u00f6\u00dfe":1311},{"Zug":"ICE 541","Fahrzeit inkl. Versp\u00e4tungen [min]":41.6666666667,"Versp\u00e4tung Abfahrt [min]":7.0,"Versp\u00e4tung Ankunft [min]":13.6666666667,"Ausfallquote":0.5,"Stichprobengr\u00f6\u00dfe":6},{"Zug":"MSM","Fahrzeit inkl. Versp\u00e4tungen [min]":43.0,"Versp\u00e4tung Abfahrt [min]":3.0,"Versp\u00e4tung Ankunft [min]":9.0,"Ausfallquote":0.0,"Stichprobengr\u00f6\u00dfe":1}]