[{"Zug":"IC 2173","Fahrzeit inkl. Versp\u00e4tungen [min]":252.7752808989,"Versp\u00e4tung Abfahrt [min]":0.6516853933,"Versp\u00e4tung Ankunft [min]":6.7415730337,"Ausfallquote":0.0326086957,"Stichprobengr\u00f6\u00dfe":92},{"Zug":"IC 2175","Fahrzeit inkl. Versp\u00e4tungen [min]":258.3260869565,"Versp\u00e4tung Abfahrt [min]":0.8369565217,"Versp\u00e4tung Ankunft [min]":10.7282608696,"Ausfallquote":0.0,"Stichprobengr\u00f6\u00dfe":92},{"Zug":"IC 2177","Fahrzeit inkl. Versp\u00e4tungen [min]":254.2272727273,"Versp\u00e4tung Abfahrt [min]":3.5909090909,"Versp\u00e4tung Ankunft [min]":11.7386363636,"Ausfallquote":0.0434782609,"Stichprobengr\u00f6\u00dfe":92},{"Zug":"IC 2271","Fahrzeit inkl. Versp\u00e4tungen [min]":258.3295454545,"Versp\u00e4tung Abfahrt [min]":1.7727272727,"Versp\u00e4tung Ankunft [min]":10.0454545455,"Ausfallquote":0.032967033,"Stichprobengr\u00f6\u00dfe":91},{"Zug":"IC 2275","Fahrzeit inkl. Versp\u00e4tungen [min]":253.4605263158,"Versp\u00e4tung Abfahrt [min]":2.7368421053,"Versp\u00e4tung Ankunft [min]":14.9342105263,"Ausfallquote":0.012987013,"Stichprobengr\u00f6\u00dfe":77},{"Zug":"IC 2179","Fahrzeit inkl. Versp\u00e4tungen [min]":249.8727272727,"Versp\u00e4tung Abfahrt [min]":0.9818181818,"Versp\u00e4tung Ankunft [min]":10.1818181818,"Ausfallquote":0.0350877193,"Stichprobengr\u00f6\u00dfe":57},{"Zug":"IC 2273","Fahrzeit inkl. Versp\u00e4tungen [min]":247.8367346939,"Versp\u00e4tung Abfahrt [min]":1.5306122449,"Versp\u00e4tung Ankunft [min]":5.8979591837,"Ausfallquote":0.0392156863,"Stichprobengr\u00f6\u00dfe":51},{"Zug":"IC 2473","Fahrzeit inkl. Versp\u00e4tungen [min]":337.0,"Versp\u00e4tung Abfahrt [min]":1.5,"Versp\u00e4tung Ankunft [min]":-7.5,"Ausfallquote":0.5,"Stichprobengr\u00f6\u00dfe":8}]