[{"Zug":"ICE 591","Fahrzeit inkl. Versp\u00e4tungen [min]":336.2380952381,"Versp\u00e4tung Abfahrt [min]":2.5714285714,"Versp\u00e4tung Ankunft [min]":12.1904761905,"Ausfallquote":0.0869565217,"Stichprobengr\u00f6\u00dfe":23},{"Zug":"IC 2375","Fahrzeit inkl. Versp\u00e4tungen [min]":355.0666666667,"Versp\u00e4tung Abfahrt [min]":6.3333333333,"Versp\u00e4tung Ankunft [min]":19.4,"Ausfallquote":0.1176470588,"Stichprobengr\u00f6\u00dfe":17},{"Zug":"ICE 1577","Fahrzeit inkl. Versp\u00e4tungen [min]":354.9230769231,"Versp\u00e4tung Abfahrt [min]":2.2307692308,"Versp\u00e4tung Ankunft [min]":10.1538461538,"Ausfallquote":0.2352941176,"Stichprobengr\u00f6\u00dfe":17},{"Zug":"ICE 699","Fahrzeit inkl. Versp\u00e4tungen [min]":621.0,"Versp\u00e4tung Abfahrt [min]":10.5,"Versp\u00e4tung Ankunft [min]":12.5,"Ausfallquote":0.3333333333,"Stichprobengr\u00f6\u00dfe":3}]