[{"Zug":"ICE 277","Fahrzeit inkl. Versp\u00e4tungen [min]":263.2317073171,"Versp\u00e4tung Abfahrt [min]":3.1219512195,"Versp\u00e4tung Ankunft [min]":7.3170731707,"Ausfallquote":0.0681818182,"Stichprobengr\u00f6\u00dfe":88},{"Zug":"ICE 279","Fahrzeit inkl. Versp\u00e4tungen [min]":266.9518072289,"Versp\u00e4tung Abfahrt [min]":3.3855421687,"Versp\u00e4tung Ankunft [min]":10.3012048193,"Ausfallquote":0.0568181818,"Stichprobengr\u00f6\u00dfe":88},{"Zug":"ICE 373","Fahrzeit inkl. Versp\u00e4tungen [min]":269.4886363636,"Versp\u00e4tung Abfahrt [min]":4.0340909091,"Versp\u00e4tung Ankunft [min]":13.4886363636,"Ausfallquote":0.0,"Stichprobengr\u00f6\u00dfe":88},{"Zug":"ICE 375","Fahrzeit inkl. Versp\u00e4tungen [min]":267.4941176471,"Versp\u00e4tung Abfahrt [min]":3.9529411765,"Versp\u00e4tung Ankunft [min]":11.4470588235,"Ausfallquote":0.0340909091,"Stichprobengr\u00f6\u00dfe":88},{"Zug":"ICE 377","Fahrzeit inkl. Versp\u00e4tungen [min]":273.7764705882,"Versp\u00e4tung Abfahrt [min]":4.4588235294,"Versp\u00e4tung Ankunft [min]":15.3058823529,"Ausfallquote":0.0340909091,"Stichprobengr\u00f6\u00dfe":88},{"Zug":"ICE 271","Fahrzeit inkl. Versp\u00e4tungen [min]":367.2976190476,"Versp\u00e4tung Abfahrt [min]":3.9166666667,"Versp\u00e4tung Ankunft [min]":9.5,"Ausfallquote":0.0344827586,"Stichprobengr\u00f6\u00dfe":87},{"Zug":"ICE 371","Fahrzeit inkl. Versp\u00e4tungen [min]":269.8571428571,"Versp\u00e4tung Abfahrt [min]":4.1071428571,"Versp\u00e4tung Ankunft [min]":14.0595238095,"Ausfallquote":0.0344827586,"Stichprobengr\u00f6\u00dfe":87},{"Zug":"ICE 275","Fahrzeit inkl. Versp\u00e4tungen [min]":263.1071428571,"Versp\u00e4tung Abfahrt [min]":3.1428571429,"Versp\u00e4tung Ankunft [min]":7.25,"Ausfallquote":0.1111111111,"Stichprobengr\u00f6\u00dfe":63},{"Zug":"ICE 1279","Fahrzeit inkl. Versp\u00e4tungen [min]":264.6153846154,"Versp\u00e4tung Abfahrt [min]":6.2307692308,"Versp\u00e4tung Ankunft [min]":11.2307692308,"Ausfallquote":0.0,"Stichprobengr\u00f6\u00dfe":13},{"Zug":"ICE 101","Fahrzeit inkl. Versp\u00e4tungen [min]":405.3333333333,"Versp\u00e4tung Abfahrt [min]":3.3333333333,"Versp\u00e4tung Ankunft [min]":22.0,"Ausfallquote":0.0,"Stichprobengr\u00f6\u00dfe":3}]